MANIFEST.in
README.txt
setup.py
XStatic_ChartNew.js.egg-info/PKG-INFO
XStatic_ChartNew.js.egg-info/SOURCES.txt
XStatic_ChartNew.js.egg-info/dependency_links.txt
XStatic_ChartNew.js.egg-info/namespace_packages.txt
XStatic_ChartNew.js.egg-info/not-zip-safe
XStatic_ChartNew.js.egg-info/top_level.txt
xstatic/__init__.py
xstatic/pkg/__init__.py
xstatic/pkg/chartnew_js/__init__.py
xstatic/pkg/chartnew_js/__init__.pyc
xstatic/pkg/chartnew_js/data/ChartNew.js
xstatic/pkg/chartnew_js/data/ChartNew.min.js