Metadata-Version: 1.0
Name: XStatic-ChartNew.js
Version: 0.3.0.0
Summary: ChartNew.js 0.3.0 (XStatic packaging standard)
Home-page: https://github.com/FVANCOP/ChartNew.js/
Author: Benjamin Dauvergne
Author-email: bdauvergne@entrouvert.com
License: (same as ChartNew.js)
Keywords: chartnew_js xstatic
Platform: any
